{"f602d7bc-b587-4331-9d63-f8750f78dc92": {"informacion_personal": {"user_id": "COL2635153", "genero": "Masculino", "nombres": "Alberto Alberto", "apellidos": "Gomez Clark", "lugar_nacimiento": "Argentina, Salta", "estado_civil": "Divorciado", "edad": 29, "religion": "Judaísmo", "postura_politica": "Conservadurismo"}, "informacion_demografica": {"profesiones": ["Electricista"], "edad": 87, "lugar_nacimiento": "Argentina, Mar del Plata"}, "gustos": {"hobbies": ["Escalada en hielo", "Kin-ball", "Magia", "Spongee", "Sumo"], "colores_favoritos": ["Turquesa"], "equipo_futbol": ["Real Madrid (España)"], "mascotas": ["Chinchilla"], "modelos_autos": ["Mercedes-Benz Clase A", "Honda Civic", "Mazda 3"], "paise_conocidos": ["Maldivas", "Costa Rica"]}, "salud": {"enfermedades_raras": [], "alergias": ["Alergia al látex", "Alergia a las picaduras de insectos", "Alergia al moho"], "deportes_practicados": ["Skateboarding", "Tenis", "Vóley"]}, "habilidades": {"habilidades_tecnicas": ["Manejo de CRM", "Desarrollo móvil", "Redes y seguridad informática", "Cloud computing (AWS, Google Cloud, etc.)", "Arquitectura de software"], "habilidades_personales": ["Trabajo en equipo", "Organización", "Habilidades interpersonales", "Gestión del estrés", "Responsabilidad"], "habilidades_varias": []}}}