{"5be16b67-87e3-46a2-9037-2c29f537ce38": {"informacion_personal": {"user_id": "COL3204028", "genero": "Femenino", "nombres": "Alison Ashley", "apellidos": "Kennedy Cruz", "lugar_nacimiento": "Peru, Iquitos", "estado_civil": "Casado", "edad": 52, "religion": "Hinduismo", "postura_politica": "Anarquismo"}, "informacion_demografica": {"profesiones": ["Pintor"], "edad": 58, "lugar_nacimiento": "Brasil, Recife"}, "gustos": {"hobbies": ["Wrestling", "Inmersiones"], "colores_favoritos": ["Oliva", "Marrón", "Verde"], "equipo_futbol": ["Barcelona SC (Ecuador)"], "mascotas": ["Tarántula", "Iguana"], "modelos_autos": ["Kia Rio", "Chevrolet Onix"], "paise_conocidos": ["Ghana", "Somalia", "República Sudafricana", "Ciudad del Vaticano", "Armenia", "Yemen", "Chad", "Nigeria", "Lituania", "Rusia", "Hungría", "Ninguno", "Honduras", "Mónaco"]}, "salud": {"enfermedades_raras": ["Enfermedad de Niemann-Pick", "Síndrome de Angelman", "Síndrome de Patau"], "alergias": [], "deportes_practicados": ["Atletismo"]}, "habilidades": {"habilidades_tecnicas": ["SEO/SEM", "Análisis de datos"], "habilidades_personales": ["Liderazgo", "Gestión del tiempo"], "habilidades_varias": ["Conocimientos de vino", "Cocina", "Escritura creativa"]}}}