{"6eacd825-1e9b-48c9-a9d7-f9ff04b4d19f": {"informacion_personal": {"user_id": "COL3961298", "genero": "Femenino", "nombres": "Eliana Helen", "apellidos": "Nguyen Watson", "lugar_nacimiento": "Ecuador, Santo Domingo", "estado_civil": "Viudo", "edad": 53, "religion": "Sijismo", "postura_politica": "Centro"}, "informacion_demografica": {"profesiones": ["Abogado", "Veterinario", "Carpintero"], "edad": 70, "lugar_nacimiento": "Colombia, Ibagué"}, "gustos": {"hobbies": ["Cycle polo", "Stoolball", "Pilates"], "colores_favoritos": ["Rosa", "Coral"], "equipo_futbol": ["América (México)"], "mascotas": ["Hurón", "Pez", "Ninguno", "Pájaro", "Rana"], "modelos_autos": [], "paise_conocidos": ["Timor Oriental", "Uganda", "Nueva Zelanda", "Zimbabue", "República del Congo", "Noruega", "Bolivia"]}, "salud": {"enfermedades_raras": ["Esclerosis lateral amiotrófica (ELA)", "Hipertensión pulmonar primaria"], "alergias": [], "deportes_practicados": ["Fútbol"]}, "habilidades": {"habilidades_tecnicas": ["Diseño gráfico", "Testing de software", "Manejo de bases de datos"], "habilidades_personales": ["Manejo de conflictos"], "habilidades_varias": []}}}