{"56f95b64-76b1-43b9-bf4e-9efea5ffab87": {"informacion_personal": {"user_id": "COL5495131", "genero": "Masculino", "nombres": "Oliver Henry", "apellidos": "Simpson Cook", "lugar_nacimiento": "Peru, Ica", "estado_civil": "Soltero", "edad": 31, "religion": "Espiritismo", "postura_politica": "Centro"}, "informacion_demografica": {"profesiones": ["Dentista", "Arquitecto", "Enfermero"], "edad": 70, "lugar_nacimiento": "Brasil, Salvador"}, "gustos": {"hobbies": ["Bodybuilding", "Czech handball", "Paralympic volleyball", "Beach handball", "Bailar"], "colores_favoritos": ["Oliva", "Coral", "Blanco"], "equipo_futbol": ["América (México)"], "mascotas": ["Rata", "Chinchilla", "Tarántula", "Pez", "Cerdito miniatura"], "modelos_autos": [], "paise_conocidos": ["Irlanda", "Kuwait", "Mozambique", "Santo Tomé y Príncipe", "Canadá", "Granada", "Surinam", "República del Congo", "Suazilandia", "Vietnam", "Lesoto", "Baréin", "Tuvalu", "Estados Unidos", "República Centroafricana", "Dinamarca", "Irak", "Micronesia", "Moldavia"]}, "salud": {"enfermedades_raras": ["Enfermedad de Gaucher", "Síndrome de Marfan"], "alergias": ["Alergia a la leche", "Alergia a las picaduras de insectos"], "deportes_practicados": ["Escalada", "Natación", "Gimnasia"]}, "habilidades": {"habilidades_tecnicas": ["Edición de video", "Administración de sistemas", "Testing de software", "Manejo de software de diseño (Illustrator, Photoshop, etc.)", "Ingeniería de hardware"], "habilidades_personales": [], "habilidades_varias": ["Yoga", "Primeros auxilios", "Escalada", "Fotografía", "Cocina"]}}}