{"720b2087-9ca6-4fa8-810d-d04925be323e": {"informacion_personal": {"user_id": "COL6095323", "genero": "Masculino", "nombres": "Elias Jacob", "apellidos": "Cox Foster", "lugar_nacimiento": "Argentina, San Juan", "estado_civil": "Separado", "edad": 53, "religion": "Budismo", "postura_politica": "Socialismo"}, "informacion_demografica": {"profesiones": ["Abogado"], "edad": 84, "lugar_nacimiento": "Brasil, Manaus"}, "gustos": {"hobbies": ["Real Tennis", "Escribir"], "colores_favoritos": ["Naranja", "Rosa"], "equipo_futbol": ["Alianza Lima (Perú)"], "mascotas": ["Chinchilla", "Rata", "Hamster"], "modelos_autos": ["Honda Civic", "Mercedes-Benz Clase A", "Mazda 3", "Audi A3"], "paise_conocidos": []}, "salud": {"enfermedades_raras": ["Fibrosis quística"], "alergias": ["Alergia a los frutos secos", "Alergia a las picaduras de insectos", "Alergia a los ácaros"], "deportes_practicados": ["Hockey"]}, "habilidades": {"habilidades_tecnicas": [], "habilidades_personales": [], "habilidades_varias": ["Deportes", "Mecánica básica", "Dibujo y pintura", "Costura"]}}}