{"4940ebd2-a703-4844-8215-b4ea8f81c0a3": {"informacion_personal": {"user_id": "COL6544285", "genero": "Masculino", "nombres": "Miguel Oscar", "apellidos": "Hart Hunt", "lugar_nacimiento": "Colombia, Cali", "estado_civil": "Viudo", "edad": 85, "religion": "Confucianismo", "postura_politica": "Centro"}, "informacion_demografica": {"profesiones": ["Fotógrafo", "Arquitecto", "Agricultor"], "edad": 61, "lugar_nacimiento": "Brasil, Belo Horizonte"}, "gustos": {"hobbies": ["Pickleball", "Vigoro", "Fistball", "Patinaje"], "colores_favoritos": ["Verde"], "equipo_futbol": ["Universitario (Perú)"], "mascotas": [], "modelos_autos": ["Hyundai Accent"], "paise_conocidos": ["Estados Unidos", "Turkmenistán", "Catar", "Vietnam", "Mónaco", "Finlandia", "Tuvalu", "Armenia"]}, "salud": {"enfermedades_raras": [], "alergias": ["Alergia al perfume"], "deportes_practicados": []}, "habilidades": {"habilidades_tecnicas": ["Inteligencia artificial", "Machine learning", "Arquitectura de software"], "habilidades_personales": [], "habilidades_varias": ["Artes marciales", "Fotografía"]}}}