{"961b82c9-4eed-4389-b114-1085d6f50b84": {"informacion_personal": {"user_id": "COL7946549", "genero": "Masculino", "nombres": "Aaron Joseph", "apellidos": "Hall Wright", "lugar_nacimiento": "Colombia, Bucaramanga", "estado_civil": "Comprometido", "edad": 89, "religion": "Ninguna", "postura_politica": "Liberalismo"}, "informacion_demografica": {"profesiones": ["Psicólogo", "Carpintero", "Bombero"], "edad": 46, "lugar_nacimiento": "Argentina, Córdoba"}, "gustos": {"hobbies": ["Judo", "Senderismo"], "colores_favoritos": ["Plateado", "Oliva", "Dorado"], "equipo_futbol": ["Flamengo (Brasil)"], "mascotas": ["Rana", "Ninguno", "Iguana"], "modelos_autos": ["Volkswagen Gol", "Nissan Versa", "Kia Rio", "Toyota Hilux"], "paise_conocidos": ["Vanuatu", "Panamá", "República Democrática del Congo", "Costa de Marfil", "Papúa Nueva Guinea", "Corea del Sur"]}, "salud": {"enfermedades_raras": ["Enfermedad de Huntington", "Distrofia muscular de Duchenne"], "alergias": ["Alergia a los sulfamidas", "Alergia al calor"], "deportes_practicados": ["Boxeo"]}, "habilidades": {"habilidades_tecnicas": ["Desarrollo de videojuegos", "Administración de sistemas"], "habilidades_personales": ["Pensamiento crítico", "Comunicación efectiva"], "habilidades_varias": ["Primeros auxilios"]}}}