{"9d74101c-a629-4500-9304-ce738f4a378b": {"informacion_personal": {"user_id": "ECU2956353", "genero": "Femenino", "nombres": "Ariel Brenda", "apellidos": "Jones Sanchez", "lugar_nacimiento": "Argentina, La Plata", "estado_civil": "Casado", "edad": 22, "religion": "Confucianismo", "postura_politica": "Centro"}, "informacion_demografica": {"profesiones": ["Periodista", "Programador", "Contador"], "edad": 82, "lugar_nacimiento": "Peru, Ica"}, "gustos": {"hobbies": ["Fistball", "Racketlon", "Kabaddi", "Bailar", "Origami"], "colores_favoritos": ["Azul", "Coral", "Turquesa"], "equipo_futbol": ["Independiente Santa Fe (Colombia)"], "mascotas": ["Erizo", "Axolote", "Geco", "Rana"], "modelos_autos": ["Chevrolet Onix", "Ford F-150"], "paise_conocidos": ["Siria", "Catar", "Omán", "Hungría", "Yibuti", "República Dominicana", "Georgia", "Italia", "Zambia", "Perú", "San Cristóbal y Nieves"]}, "salud": {"enfermedades_raras": [], "alergias": ["Alergia al polen", "Alergia al frío"], "deportes_practicados": ["Baloncesto", "Natación", "Béisbol"]}, "habilidades": {"habilidades_tecnicas": ["Desarrollo móvil", "Programación", "Desarrollo web", "Redes y seguridad informática"], "habilidades_personales": [], "habilidades_varias": ["Costura", "Primeros auxilios", "Carpintería"]}}}