{"3ced5b29-cb07-4bc0-8995-41661da22222": {"informacion_personal": {"user_id": "ECU6341777", "genero": "Femenino", "nombres": "Elena Sara", "apellidos": "Elliott Perkins", "lugar_nacimiento": "Colombia, Barranquilla", "estado_civil": "Casado", "edad": 42, "religion": "Hinduismo", "postura_politica": "Fascismo"}, "informacion_demografica": {"profesiones": [], "edad": 101, "lugar_nacimiento": "Argentina, Tucumán"}, "gustos": {"hobbies": ["Skydiving"], "colores_favoritos": ["Morado"], "equipo_futbol": ["Cruz Azul (México)"], "mascotas": ["Cerdito miniatura"], "modelos_autos": ["Renault Kwid", "Chevrolet Onix", "Toyota Hilux"], "paise_conocidos": ["Brunéi", "Antigua y Barbuda", "Angola", "República Sudafricana", "Bosnia y Herzegovina", "Islandia", "Malasia"]}, "salud": {"enfermedades_raras": ["Síndrome de Sturge-Weber", "Síndrome de Patau", "Síndrome de Prader-Willi"], "alergias": ["Alergia a las picaduras de insectos"], "deportes_practicados": ["Equitación"]}, "habilidades": {"habilidades_tecnicas": ["Programación", "Ingeniería de hardware", "SEO/SEM", "Diseño gráfico", "Machine learning"], "habilidades_personales": ["Perseverancia", "Optimismo", "Empatía", "Manejo de conflictos", "Capacidad de aprendizaje"], "habilidades_varias": ["Jardinería", "Ninguno", "Cocina", "Deportes", "Buceo"]}}}