{"c1c5c298-c93a-4bb4-a23e-e5a74274f287": {"informacion_personal": {"user_id": "ECU7167476", "genero": "Femenino", "nombres": "Vivian Nicole", "apellidos": "Coleman Nguyen", "lugar_nacimiento": "Ecuador, Manta", "estado_civil": "Unión libre", "edad": 29, "religion": "Espiritismo", "postura_politica": "Fascismo"}, "informacion_demografica": {"profesiones": ["Fotógrafo"], "edad": 94, "lugar_nacimiento": "Brasil, Brasília"}, "gustos": {"hobbies": ["Yak polo", "Softball", "Softcrosse", "Escalada", "Voleibol de playa"], "colores_favoritos": ["Fucsia", "Turquesa", "Amarillo"], "equipo_futbol": ["Atlético Nacional (Colombia)"], "mascotas": ["Tortuga"], "modelos_autos": ["Toyota Hilux", "Mercedes-Benz Clase A", "Seat Ibiza", "Fiat Palio"], "paise_conocidos": ["Venezuela", "Liberia", "Colombia", "Bosnia y Herzegovina", "Hungría", "Guinea ecuatorial", "Eslovaquia", "Granada", "Pakistán", "Letonia", "Uruguay", "Haití", "Timor Oriental", "Madagascar", "Malaui", "Guyana"]}, "salud": {"enfermedades_raras": ["Síndrome de Sturge-Weber"], "alergias": ["Alergia al polvo", "Alergia a los sulfamidas", "Alergia al polen"], "deportes_practicados": []}, "habilidades": {"habilidades_tecnicas": ["Manejo de software de diseño (Illustrator, Photoshop, etc.)", "Análisis de datos", "Diseño gráfico", "Desarrollo de realidad virtual y aumentada"], "habilidades_personales": ["Trabajo en equipo", "Honestidad"], "habilidades_varias": ["Buceo", "Cerámica", "Escalada"]}}}