{"1fb502f6-96f6-44ee-974a-c1adfdc77ab8": {"informacion_personal": {"user_id": "ECU8819313", "genero": "Femenino", "nombres": "Juliana Annabelle", "apellidos": "Ward Sullivan", "lugar_nacimiento": "Brasil, Brasília", "estado_civil": "Separado", "edad": 49, "religion": "Espiritismo", "postura_politica": "Izquierda"}, "informacion_demografica": {"profesiones": ["Pescador"], "edad": 55, "lugar_nacimiento": "Ecuador, Loja"}, "gustos": {"hobbies": ["Equitación", "Fútbol Australiano", "Box lacrosse"], "colores_favoritos": ["Rojo"], "equipo_futbol": ["Barcelona SC (Ecuador)"], "mascotas": ["Cerdito miniatura", "Tarántula", "Pájaro"], "modelos_autos": ["Toyota Hilux", "Honda Civic", "Citroën C3"], "paise_conocidos": ["Burkina Faso", "Malaui", "Madagascar", "Tanzania", "República Sudafricana", "China", "Luxemburgo", "Nigeria", "Seychelles", "Siria", "Chipre", "Argentina", "Liechtenstein", "Benín", "República Centroafricana", "Etiopía"]}, "salud": {"enfermedades_raras": ["Síndrome de Guillain-Barré"], "alergias": ["Alergia a la penicilina", "Alergia al polvo", "Alergia a los medicamentos"], "deportes_practicados": ["Esquí"]}, "habilidades": {"habilidades_tecnicas": ["Analítica web", "Diseño gráfico", "Ingeniería de hardware", "Manejo de software de diseño (Illustrator, Photoshop, etc.)", "Desarrollo de videojuegos"], "habilidades_personales": ["Trabajo en equipo", "Gestión del estrés", "Optimismo", "Capacidad de aprendizaje", "Habilidad de negociación"], "habilidades_varias": ["Deportes", "Yoga", "Idiomas", "Tocar un instrumento musical", "Escalada"]}}}