{"cd99fe61-7dd0-4f41-8a46-2750a1acbea6": {"informacion_personal": {"user_id": "ECU9086693", "genero": "Femenino", "nombres": "Isabel Melissa", "apellidos": "Bradley Perkins", "lugar_nacimiento": "Peru, Chiclayo", "estado_civil": "Viudo", "edad": 81, "religion": "Ninguna", "postura_politica": "Socialismo"}, "informacion_demografica": {"profesiones": ["Fotógrafo", "Mecánico"], "edad": 59, "lugar_nacimiento": "Ecuador, Cuenca"}, "gustos": {"hobbies": ["Kickball", "Ringette"], "colores_favoritos": ["Coral", "Celeste"], "equipo_futbol": ["Palmeiras (Brasil)"], "mascotas": ["Rana"], "modelos_autos": ["Opel Corsa", "Mazda 3"], "paise_conocidos": ["Austria", "Mauritania", "Fiyi", "Camboya", "Nueva Zelanda", "Australia", "Tanzania", "Libia", "Ghana", "Portugal", "Costa Rica", "Líbano", "Malí", "Liechtenstein", "Samoa", "Togo", "Alemania", "Suiza", "Marruecos"]}, "salud": {"enfermedades_raras": [], "alergias": [], "deportes_practicados": []}, "habilidades": {"habilidades_tecnicas": ["Machine learning", "Desarrollo de videojuegos", "Ciberseguridad", "Desarrollo de realidad virtual y aumentada"], "habilidades_personales": ["Habilidades interpersonales", "Honestidad", "Resolución de problemas", "Organización"], "habilidades_varias": ["Conocimientos de vino", "Costura", "Escalada", "Tocar un instrumento musical", "Jardinería"]}}}