{"bcec698a-ea31-44d5-ac87-6dd1443fed3d": {"informacion_personal": {"user_id": "MEX0149498", "genero": "Femenino", "nombres": "Valentina Allison", "apellidos": "Hunt Lewis", "lugar_nacimiento": "Argentina, Córdoba", "estado_civil": "Unión libre", "edad": 23, "religion": "Budismo", "postura_politica": "Populismo"}, "informacion_demografica": {"profesiones": ["Policía", "Profesor"], "edad": 101, "lugar_nacimiento": "Ecuador, Santo Domingo"}, "gustos": {"hobbies": ["Squash", "Cerámica"], "colores_favoritos": ["Naranja"], "equipo_futbol": ["Ninguno"], "mascotas": ["Pájaro", "Cuy"], "modelos_autos": ["Hyundai Accent", "Renault Kwid", "Peugeot 208", "Chevrolet Onix"], "paise_conocidos": ["Ninguno", "Paraguay", "Antigua y Barbuda"]}, "salud": {"enfermedades_raras": [], "alergias": ["Alergia al moho", "Alergia al sol", "Alergia al níquel", "Alergia a las picaduras de insectos"], "deportes_practicados": ["Tenis"]}, "habilidades": {"habilidades_tecnicas": ["Desarrollo web", "Programación", "Desarrollo de videojuegos", "Analítica web"], "habilidades_personales": [], "habilidades_varias": []}}}