{"4d6882f7-9a1b-4be9-a452-5cb7128a31cc": {"informacion_personal": {"user_id": "MEX1727463", "genero": "Masculino", "nombres": "Jonas Landon", "apellidos": "Hughes Hernandez", "lugar_nacimiento": "Peru, Huancayo", "estado_civil": "Unión libre", "edad": 53, "religion": "Hinduismo", "postura_politica": "Populismo"}, "informacion_demografica": {"profesiones": ["Panadero"], "edad": 57, "lugar_nacimiento": "Argentina, Salta"}, "gustos": {"hobbies": ["Roque", "Stoolball", "Basque pelota", "Canoe polo"], "colores_favoritos": ["Rojo", "Dorado"], "equipo_futbol": ["Sao Paulo FC (Brasil)"], "mascotas": ["Perro", "Tortuga", "Pájaro"], "modelos_autos": [], "paise_conocidos": ["Turkmenistán", "Gabón", "Reino Unido", "Liberia", "Chile", "Rumanía", "Brunéi", "Costa de Marfil", "Pakistán", "España", "Estonia", "Belice", "República Centroafricana", "Portugal", "Corea del Norte", "Kazajistán", "Eslovaquia"]}, "salud": {"enfermedades_raras": ["Ninguna", "Enfermedad de Niemann-Pick", "Síndrome de Marfan"], "alergias": ["Alergia a los mariscos", "Alergia a los sulfamidas", "Alergia al polen", "Alergia al níquel"], "deportes_practicados": ["Gimnasia", "Surf"]}, "habilidades": {"habilidades_tecnicas": ["Arquitectura de software"], "habilidades_personales": [], "habilidades_varias": ["Idiomas", "Escritura creativa", "Cerámica", "Costura"]}}}