{"26ee4728-8a77-477f-95d4-8e6ff6bf69eb": {"informacion_personal": {"user_id": "MEX1760800", "genero": "Femenino", "nombres": "Sophie Ariel", "apellidos": "Price Berry", "lugar_nacimiento": "Argentina, San Juan", "estado_civil": "Comprometido", "edad": 105, "religion": "Cristianismo", "postura_politica": "Liberalismo"}, "informacion_demografica": {"profesiones": ["Médico", "Psicólogo", "Agricultor"], "edad": 49, "lugar_nacimiento": "Colombia, Cúcuta"}, "gustos": {"hobbies": ["Pasear a mascotas", "Volleyball", "Coleccionismo"], "colores_favoritos": ["Celeste", "Azul"], "equipo_futbol": ["River Plate (Argentina)"], "mascotas": ["Pez"], "modelos_autos": ["Volkswagen Gol", "Suzuki Swift"], "paise_conocidos": ["Turkmenistán", "Austria", "Zambia", "Cabo Verde", "Italia", "Vietnam", "Rusia", "Emiratos Árabes Unidos", "Jordania", "Ciudad del Vaticano", "Japón", "Barbados", "Túnez", "Zimbabue", "Nepal", "Bulgaria", "Eritrea", "Costa Rica", "Arabia Saudita"]}, "salud": {"enfermedades_raras": ["Síndrome de Prader-Willi", "Enfermedad de Niemann-Pick", "Fibrosis quística"], "alergias": ["Alergia al sol", "Alergia al polvo", "Alergia a los frutos secos"], "deportes_practicados": []}, "habilidades": {"habilidades_tecnicas": [], "habilidades_personales": ["Proactividad", "Capacidad de aprendizaje", "Adaptabilidad", "Honestidad", "Responsabilidad"], "habilidades_varias": []}}}