{"25ef96ed-581c-482c-b4c2-9bb44cdbf478": {"informacion_personal": {"user_id": "MEX2946933", "genero": "Femenino", "nombres": "Jacqueline Evelyn", "apellidos": "Henry Cook", "lugar_nacimiento": "Brasil, Manaus", "estado_civil": "Divorciado", "edad": 99, "religion": "Espiritismo", "postura_politica": "Ninguna"}, "informacion_demografica": {"profesiones": [], "edad": 65, "lugar_nacimiento": "Argentina, Mendoza"}, "gustos": {"hobbies": ["Ping-pong"], "colores_favoritos": ["Gris", "Lavanda"], "equipo_futbol": ["Palmeiras (Brasil)"], "mascotas": ["Hamster"], "modelos_autos": ["Mazda 3"], "paise_conocidos": ["República Centroafricana", "Bielorrusia", "San Cristóbal y Nieves", "Bulgaria", "Guinea", "Bután", "Islas Marshall", "Kazajistán", "República Dominicana", "Maldivas", "San Marino", "Chad", "Laos", "Marruecos", "Países Bajos", "Vietnam"]}, "salud": {"enfermedades_raras": ["Síndrome de Prader-Willi", "Síndrome de Angelman"], "alergias": ["Alergia al polvo"], "deportes_practicados": []}, "habilidades": {"habilidades_tecnicas": ["Desarrollo de videojuegos", "Marketing digital", "Machine learning", "Programación", "Analítica web"], "habilidades_personales": ["Iniciativa"], "habilidades_varias": ["Idiomas", "Carpintería"]}}}