{"af67fda2-cc2d-4b24-b2cd-633145e4e900": {"informacion_personal": {"user_id": "MEX3287455", "genero": "Masculino", "nombres": "Hector Javier", "apellidos": "Matthews Coleman", "lugar_nacimiento": "Colombia, Cali", "estado_civil": "Soltero", "edad": 26, "religion": "Sijismo", "postura_politica": "Liberalismo"}, "informacion_demografica": {"profesiones": [], "edad": 80, "lugar_nacimiento": "Brasil, Salvador"}, "gustos": {"hobbies": ["Tchoukball", "Horseball", "Cazar"], "colores_favoritos": ["Rojo", "Coral"], "equipo_futbol": ["Barcelona SC (Ecuador)"], "mascotas": ["Conejo", "Hurón", "Erizo", "Hamster", "Axolote"], "modelos_autos": ["Renault Kwid", "BMW Serie 3", "Toyota Hilux", "Mercedes-Benz Clase A"], "paise_conocidos": ["Estados Unidos", "Brasil", "Suiza", "Andorra", "Libia", "Chipre", "Suazilandia", "Bután", "Tailandia", "Noruega", "Irán", "Tuvalu", "Grecia", "Palaos", "Bielorrusia"]}, "salud": {"enfermedades_raras": ["Enfermedad de Huntington", "Enfermedad de Niemann-Pick"], "alergias": ["Alergia a los sulfamidas", "Alergia al polvo", "Alergia al perfume"], "deportes_practicados": []}, "habilidades": {"habilidades_tecnicas": ["Ciberseguridad", "Administración de sistemas", "Programación", "Desarrollo de videojuegos"], "habilidades_personales": ["Gestión del estrés", "Responsabilidad"], "habilidades_varias": ["Jardinería", "Carpintería"]}}}