{"1bd336bf-3de0-4517-abd3-6aaaeba86862": {"informacion_personal": {"user_id": "MEX4080579", "genero": "Femenino", "nombres": "Dulce Elise", "apellidos": "Brooks Cooper", "lugar_nacimiento": "Peru, Piura", "estado_civil": "Soltero", "edad": 85, "religion": "Jainismo", "postura_politica": "Centro"}, "informacion_demografica": {"profesiones": ["Arquitecto", "Dentista", "Pintor"], "edad": 94, "lugar_nacimiento": "Peru, Huancayo"}, "gustos": {"hobbies": ["Tejer", "Speed-ball", "Cycle polo", "Judo", "Yoga"], "colores_favoritos": ["Azul"], "equipo_futbol": ["Alianza Lima (Perú)"], "mascotas": ["Rata", "Rana", "Cerdito miniatura", "Axolote", "Iguana"], "modelos_autos": ["Honda Civic", "Mercedes-Benz Clase A", "Fiat Palio"], "paise_conocidos": ["Egipto", "Hungría", "Maldivas"]}, "salud": {"enfermedades_raras": ["Síndrome de Patau", "Enfermedad de Niemann-Pick", "Ninguna"], "alergias": ["Alergia al níquel", "Alergia al látex", "Alergia a la leche"], "deportes_practicados": []}, "habilidades": {"habilidades_tecnicas": ["Desarrollo de realidad virtual y aumentada", "Arquitectura de software"], "habilidades_personales": ["Adaptabilidad"], "habilidades_varias": ["Cocina", "Tocar un instrumento musical", "Jardinería"]}}}