{"2f9033c7-6d48-4e1a-9968-bda1d279402f": {"informacion_personal": {"user_id": "MEX5781174", "genero": "Masculino", "nombres": "Randy Dante", "apellidos": "Moore Patterson", "lugar_nacimiento": "Colombia, Ibagué", "estado_civil": "Unión libre", "edad": 63, "religion": "Budismo", "postura_politica": "Comunismo"}, "informacion_demografica": {"profesiones": [], "edad": 89, "lugar_nacimiento": "Peru, Lima"}, "gustos": {"hobbies": ["Polo", "Tennis polo", "Hockey sobre hielo", "Sepak Takraw"], "colores_favoritos": ["Lavanda", "Gris"], "equipo_futbol": ["Alianza Lima (Perú)"], "mascotas": [], "modelos_autos": [], "paise_conocidos": ["Cabo Verde", "Ciudad del Vaticano", "Haití", "Fiyi", "Cuba", "Barbados", "Rumanía", "Nepal"]}, "salud": {"enfermedades_raras": ["Fibrosis quística", "Síndrome de Rett", "Progeria"], "alergias": [], "deportes_practicados": ["Atletismo", "Baloncesto", "Boxeo"]}, "habilidades": {"habilidades_tecnicas": ["Arquitectura de software", "Desarrollo de realidad virtual y aumentada"], "habilidades_personales": ["Responsabilidad", "Iniciativa", "Proactividad", "Toma de decisiones", "Perseverancia"], "habilidades_varias": ["Deportes", "Escritura creativa", "Primeros auxilios", "Conocimientos de vino", "Jardinería"]}}}