{"ddbe0171-665d-4392-8034-2eb3f45780ff": {"informacion_personal": {"user_id": "MEX9947029", "genero": "Masculino", "nombres": "Jayce Nick", "apellidos": "Franklin Foster", "lugar_nacimiento": "Ecuador, Manta", "estado_civil": "Unión libre", "edad": 71, "religion": "Budismo", "postura_politica": "Anarquismo"}, "informacion_demografica": {"profesiones": ["Ninguno", "Pintor"], "edad": 52, "lugar_nacimiento": "Colombia, Bogotá"}, "gustos": {"hobbies": ["Pilota", "Bádminton", "Throwball"], "colores_favoritos": ["Verde", "Naranja", "Blanco"], "equipo_futbol": ["Sporting Cristal (Perú)"], "mascotas": ["Geco", "Perro", "Cuy"], "modelos_autos": ["Ford F-150"], "paise_conocidos": ["Armenia", "Timor Oriental", "Uruguay", "Bahamas", "Etiopía", "Rumanía", "Suazilandia"]}, "salud": {"enfermedades_raras": ["Síndrome de Angelman"], "alergias": ["Alergia al polen", "Alergia al calor", "Alergia a los alimentos", "Alergia al perfume"], "deportes_practicados": []}, "habilidades": {"habilidades_tecnicas": [], "habilidades_personales": ["Toma de decisiones"], "habilidades_varias": ["Idiomas", "Yoga", "Buceo"]}}}