{"cbb1d8fc-a31a-42a1-b043-7e8bb699aa4f": {"informacion_personal": {"user_id": "MEX9521534", "genero": "Masculino", "nombres": "Milan Ronald", "apellidos": "Ramos Ray", "lugar_nacimiento": "Ecuador, Cuenca", "estado_civil": "Unión libre", "edad": 96, "religion": "Cristianismo", "postura_politica": "Socialismo"}, "informacion_demografica": {"profesiones": ["Carpintero", "Periodista", "Cocinero"], "edad": 70, "lugar_nacimiento": "Colombia, Cartagena"}, "gustos": {"hobbies": ["Rafting"], "colores_favoritos": ["Coral", "Plateado", "Naranja"], "equipo_futbol": ["Sao Paulo FC (Brasil)"], "mascotas": [], "modelos_autos": [], "paise_conocidos": ["Fiyi", "Suazilandia", "Hungría", "Uruguay", "Líbano", "Nueva Zelanda", "Jordania", "México"]}, "salud": {"enfermedades_raras": ["Enfermedad de Gaucher", "Síndrome de Prader-Willi", "Enfermedad de Tay-Sachs"], "alergias": ["Alergia a la leche", "Alergia a los sulfamidas"], "deportes_practicados": ["Béisbol", "Escalada", "Vóley"]}, "habilidades": {"habilidades_tecnicas": ["Administración de sistemas", "Marketing digital", "Desarrollo web", "Desarrollo de videojuegos", "Manejo de software de diseño (Illustrator, Photoshop, etc.)"], "habilidades_personales": ["Perseverancia", "Empatía", "Toma de decisiones"], "habilidades_varias": []}}}