{"72b96a12-21fa-4511-bcf2-0520924b1bf0": {"informacion_personal": {"user_id": "PER4733660", "genero": "Femenino", "nombres": "Amber Faith", "apellidos": "Campbell Evans", "lugar_nacimiento": "Peru, Cusco", "estado_civil": "Casado", "edad": 58, "religion": "Judaísmo", "postura_politica": "Centro"}, "informacion_demografica": {"profesiones": ["Ingeniero", "Bombero"], "edad": 98, "lugar_nacimiento": "Argentina, Tucumán"}, "gustos": {"hobbies": ["Three sided football", "Equitación", "Escalada en hielo", "Unicycle basketball", "Korfball"], "colores_favoritos": ["Blanco", "Rojo"], "equipo_futbol": ["Boca Juniors (Argentina)"], "mascotas": ["Ninguno", "Gato", "Cuy", "Axolote", "Cerdito miniatura"], "modelos_autos": ["Honda Civic", "Seat Ibiza", "BMW Serie 3"], "paise_conocidos": ["Costa de Marfil", "Libia", "Honduras", "Senegal", "Burundi", "Islas Marshall", "Países Bajos", "Filipinas", "Colombia", "Australia", "México", "Bulgaria", "Gabón", "Camerún", "Bosnia y Herzegovina", "Letonia", "Barbados", "Dominica"]}, "salud": {"enfermedades_raras": ["Distrofia muscular de Duchenne", "Síndrome de Edwards"], "alergias": ["Alergia al polvo"], "deportes_practicados": ["Vóley", "Skateboarding"]}, "habilidades": {"habilidades_tecnicas": ["Cloud computing (AWS, Google Cloud, etc.)", "Desarrollo de realidad virtual y aumentada", "Desarrollo móvil", "Blockchain"], "habilidades_personales": ["Manejo de conflictos", "Liderazgo"], "habilidades_varias": ["Cocina", "Artes marciales"]}}}