{"fd6f3c9c-83a2-4280-862d-20b97487b740": {"informacion_personal": {"user_id": "PER7964292", "genero": "Femenino", "nombres": "Riley Julia", "apellidos": "Davis Baker", "lugar_nacimiento": "Colombia, Barranquilla", "estado_civil": "Viudo", "edad": 46, "religion": "Judaísmo", "postura_politica": "Liberalismo"}, "informacion_demografica": {"profesiones": ["Cocinero", "Programador", "Peluquero"], "edad": 56, "lugar_nacimiento": "Colombia, Bogotá"}, "gustos": {"hobbies": ["Korfball"], "colores_favoritos": ["Gris", "Verde", "Plateado"], "equipo_futbol": ["Real Madrid (España)"], "mascotas": ["Gato", "Perro", "Ninguno", "Conejo", "Pájaro"], "modelos_autos": ["Opel Corsa", "Toyota Hilux", "Fiat Palio"], "paise_conocidos": ["Cuba", "República Checa", "Níger", "San Cristóbal y Nieves", "Chad", "Filipinas", "Suecia", "Tailandia", "Madagascar", "Palaos", "Vietnam", "Islandia", "República Centroafricana"]}, "salud": {"enfermedades_raras": [], "alergias": ["Alergia a los mariscos", "Alergia al polvo", "Alergia a los medicamentos"], "deportes_practicados": ["Skateboarding", "Hockey", "Fútbol"]}, "habilidades": {"habilidades_tecnicas": ["Edición de video"], "habilidades_personales": [], "habilidades_varias": ["Cerámica", "Fotografía", "Cocina"]}}}