{"167fb979-79bb-4bb5-af83-1734a53b8e94": {"informacion_personal": {"user_id": "PER8983341", "genero": "Masculino", "nombres": "Brent Jesse", "apellidos": "Diaz Allen", "lugar_nacimiento": "Colombia, Bogotá", "estado_civil": "Unión libre", "edad": 78, "religion": "Confucianismo", "postura_politica": "Comunismo"}, "informacion_demografica": {"profesiones": ["Pescador"], "edad": 49, "lugar_nacimiento": "Peru, Trujillo"}, "gustos": {"hobbies": ["Equitación", "Aeróbic", "Canto", "Qianball"], "colores_favoritos": ["Negro", "Celeste"], "equipo_futbol": ["América (México)"], "mascotas": [], "modelos_autos": ["Chevrolet Onix", "Kia Rio"], "paise_conocidos": ["Timor Oriental", "Ciudad del Vaticano", "Suazilandia", "Comoras", "Guyana", "Malaui", "Somalia", "Tuvalu", "Rusia", "Islandia", "Finlandia", "Mozambique", "Cabo Verde", "San Cristóbal y Nieves", "Irlanda"]}, "salud": {"enfermedades_raras": ["Síndrome de Marfan", "Histiocitosis de células de Langerhans", "Enfermedad de Wilson"], "alergias": ["Alergia a los mariscos", "Alergia al calor"], "deportes_practicados": ["Boxeo"]}, "habilidades": {"habilidades_tecnicas": ["Diseño gráfico"], "habilidades_personales": ["Iniciativa"], "habilidades_varias": ["Buceo", "Meditación", "Jardinería", "Tocar un instrumento musical", "Escalada"]}}}