{"60091ac7-692d-43e6-b8b9-7136e3ea69e2": {"informacion_personal": {"user_id": "USA0565355", "genero": "Masculino", "nombres": "Ivan Rafael", "apellidos": "Boyd Brown", "lugar_nacimiento": "Colombia, Ibagué", "estado_civil": "Unión libre", "edad": 102, "religion": "Hinduismo", "postura_politica": "Fascismo"}, "informacion_demografica": {"profesiones": ["Bombero", "Veterinario"], "edad": 45, "lugar_nacimiento": "Colombia, Santa Marta"}, "gustos": {"hobbies": ["Skateboarding", "Kin-ball", "Footvolley", "Yak polo", "Skater hockey"], "colores_favoritos": ["Rojo", "Morado"], "equipo_futbol": ["Flamengo (Brasil)"], "mascotas": [], "modelos_autos": [], "paise_conocidos": ["Irlanda", "San Vicente y las Granadinas", "Mongolia", "Kenia", "Noruega", "China", "Siria", "Bangladés", "Ciudad del Vaticano", "Angola", "Namibia", "Micronesia", "Kiribati", "San Cristóbal y Nieves", "Filipinas", "Chile"]}, "salud": {"enfermedades_raras": ["Síndrome de Prader-Willi"], "alergias": ["Alergia al frío", "Alergia a los sulfamidas", "Alergia a los medicamentos"], "deportes_practicados": ["Tenis", "Vóley"]}, "habilidades": {"habilidades_tecnicas": [], "habilidades_personales": ["Organización"], "habilidades_varias": ["Dibujo y pintura", "Yoga", "Idiomas", "Buceo"]}}}