{"e878a11b-140d-4d0f-b74d-ce39b480f673": {"informacion_personal": {"user_id": "USA0940502", "genero": "Femenino", "nombres": "Hailey Melissa", "apellidos": "Stewart Howard", "lugar_nacimiento": "Brasil, Porto Alegre", "estado_civil": "Comprometido", "edad": 89, "religion": "Jainismo", "postura_politica": "Liberalismo"}, "informacion_demografica": {"profesiones": ["Peluquero", "Periodista", "Policía"], "edad": 73, "lugar_nacimiento": "Colombia, Medellín"}, "gustos": {"hobbies": ["Wheelchair basketball", "Rugby subacuático", "Kickball"], "colores_favoritos": ["Morado", "Celeste", "Negro"], "equipo_futbol": ["América (México)"], "mascotas": ["Chinchilla", "Tortuga", "Cerdito miniatura", "Rata"], "modelos_autos": ["Peugeot 208", "Mercedes-Benz Clase A", "Nissan Versa"], "paise_conocidos": ["Malaui", "Namibia", "Mónaco", "México", "Francia", "Israel", "Reino Unido", "Liechtenstein", "Kazajistán", "Emiratos Árabes Unidos", "Guinea ecuatorial", "Papúa Nueva Guinea", "Malasia", "Botsuana", "Sudán del Sur", "Lesoto"]}, "salud": {"enfermedades_raras": [], "alergias": [], "deportes_practicados": ["Béisbol", "Baloncesto", "Skateboarding"]}, "habilidades": {"habilidades_tecnicas": ["Manejo de CRM", "Desarrollo móvil", "Manejo de bases de datos", "Analítica web", "SEO/SEM"], "habilidades_personales": ["Manejo de conflictos", "Proactividad", "Resolución de problemas", "Adaptabilidad"], "habilidades_varias": ["Primeros auxilios", "Deportes", "Meditación", "Jardinería", "Ninguno"]}}}