{"2fad8e37-2f04-4eb2-86c0-8d6a9461b768": {"informacion_personal": {"user_id": "USA1820884", "genero": "Masculino", "nombres": "George Jason", "apellidos": "Clark Johnson", "lugar_nacimiento": "Peru, Lima", "estado_civil": "Unión libre", "edad": 92, "religion": "Confucianismo", "postura_politica": "Liberalismo"}, "informacion_demografica": {"profesiones": ["Mecánico", "Bombero", "Médico"], "edad": 54, "lugar_nacimiento": "Ecuador, Manta"}, "gustos": {"hobbies": ["Escalada en roca", "Maratón"], "colores_favoritos": ["Plateado", "Azul"], "equipo_futbol": ["Cruz Azul (México)"], "mascotas": ["Tortuga", "Tarántula", "Serpiente", "Iguana"], "modelos_autos": [], "paise_conocidos": ["Vietnam", "Ghana", "Portugal", "Antigua y Barbuda", "Uzbekistán", "Argentina", "Burundi", "Filipinas"]}, "salud": {"enfermedades_raras": ["Síndrome de Rett"], "alergias": ["Alergia al látex", "Alergia al sol"], "deportes_practicados": ["Boxeo", "Fútbol", "Esquí"]}, "habilidades": {"habilidades_tecnicas": ["Analítica web", "Ciberseguridad", "Desarrollo móvil", "Manejo de software de diseño (Illustrator, Photoshop, etc.)", "Manejo de bases de datos"], "habilidades_personales": ["Adaptabilidad"], "habilidades_varias": []}}}