{"9c57214f-98d9-481f-bacc-f4729e9748be": {"informacion_personal": {"user_id": "USA2544699", "genero": "Femenino", "nombres": "Chloe Angela", "apellidos": "Holmes Romero", "lugar_nacimiento": "Brasil, Fortaleza", "estado_civil": "Casado", "edad": 96, "religion": "Ninguna", "postura_politica": "Fascismo"}, "informacion_demografica": {"profesiones": [], "edad": 66, "lugar_nacimiento": "Brasil, Curitiba"}, "gustos": {"hobbies": ["MMA", "Rafting", "Snowboarding", "Pilates"], "colores_favoritos": ["Celeste", "Dorado", "Plateado"], "equipo_futbol": ["Universitario (Perú)"], "mascotas": ["Rata", "Cerdito miniatura"], "modelos_autos": ["Renault Kwid", "Peugeot 208"], "paise_conocidos": ["Jordania", "Botsuana", "Portugal", "Timor Oriental", "Serbia", "Grecia", "Cabo Verde", "Francia", "Angola", "Jamaica"]}, "salud": {"enfermedades_raras": ["Síndrome de Edwards", "Histiocitosis de células de Langerhans", "Síndrome de Prader-Willi"], "alergias": ["Alergia a las picaduras de insectos"], "deportes_practicados": ["Golf", "Atletismo", "Boxeo"]}, "habilidades": {"habilidades_tecnicas": ["Ninguno", "Ciberseguridad", "Desarrollo de videojuegos"], "habilidades_personales": ["Toma de decisiones", "Auto motivación"], "habilidades_varias": ["Deportes", "Artes marciales", "Jardinería", "Carpintería"]}}}