{"df0478a7-1cfb-4bb1-ae37-c678aa9ae15e": {"informacion_personal": {"user_id": "USA3905249", "genero": "Masculino", "nombres": "Gustavo John", "apellidos": "Andrews Hicks", "lugar_nacimiento": "Brasil, Porto Alegre", "estado_civil": "Comprometido", "edad": 74, "religion": "Jainismo", "postura_politica": "Liberalismo"}, "informacion_demografica": {"profesiones": [], "edad": 21, "lugar_nacimiento": "Argentina, Mar del Plata"}, "gustos": {"hobbies": ["Rinkball", "Beach volleyball", "Beach rugby", "Polo acuático"], "colores_favoritos": ["Blanco", "Oliva", "Lavanda"], "equipo_futbol": ["Liga de Quito (Ecuador)"], "mascotas": ["Serpiente"], "modelos_autos": ["Renault Kwid", "Volkswagen Gol"], "paise_conocidos": ["Eritrea", "Chile", "Túnez", "Namibia", "San Cristóbal y Nieves", "Uruguay", "Uganda", "Bélgica", "Liberia", "Argentina", "Guinea-Bisáu", "República del Congo", "Rumanía", "Nueva Zelanda"]}, "salud": {"enfermedades_raras": [], "alergias": ["Alergia al níquel", "Alergia a los medicamentos", "Alergia a los frutos secos"], "deportes_practicados": ["Béisbol", "Golf"]}, "habilidades": {"habilidades_tecnicas": ["Testing de software", "Cloud computing (AWS, Google Cloud, etc.)", "Analítica web", "Ciberseguridad"], "habilidades_personales": ["Optimismo", "Manejo de conflictos"], "habilidades_varias": []}}}