{"a8ec6641-0b85-4cca-8aa1-64563f2c0a8c": {"informacion_personal": {"user_id": "USA4394434", "genero": "Femenino", "nombres": "Eva Josephine", "apellidos": "Brooks Watkins", "lugar_nacimiento": "Brasil, Manaus", "estado_civil": "Soltero", "edad": 25, "religion": "Hinduismo", "postura_politica": "Comunismo"}, "informacion_demografica": {"profesiones": ["Ninguno"], "edad": 38, "lugar_nacimiento": "Ecuador, Loja"}, "gustos": {"hobbies": ["Rugby", "Rounders", "Biathlon", "Voleibol de playa", "Muay Thai"], "colores_favoritos": ["Plateado", "Marrón"], "equipo_futbol": ["Universitario (Perú)"], "mascotas": ["Gato", "Cerdito miniatura"], "modelos_autos": ["Fiat Palio", "Chevrolet Onix", "Hyundai Accent", "Kia Rio"], "paise_conocidos": ["Siria", "Madagascar", "Afganistán", "Yemen", "Papúa Nueva Guinea", "Zimbabue", "Tuvalu", "Samoa", "Portugal", "Timor Oriental", "Costa de Marfil", "Somalia", "Kenia", "Costa Rica", "Eslovenia", "Botsuana", "Kazajistán", "Kuwait", "Emiratos Árabes Unidos", "Indonesia"]}, "salud": {"enfermedades_raras": ["Ninguna"], "alergias": ["Alergia a los mariscos", "Alergia a los sulfamidas", "Alergia al gluten"], "deportes_practicados": ["Rugby", "Fútbol"]}, "habilidades": {"habilidades_tecnicas": ["Arquitectura de software"], "habilidades_personales": ["Iniciativa", "Capacidad de aprendizaje", "Trabajo en equipo", "Proactividad", "Habilidad de negociación"], "habilidades_varias": ["Tocar un instrumento musical", "Ninguno", "Cocina", "Conocimientos de vino", "Idiomas"]}}}