{"f50be57a-0624-4e3c-99fc-545587459f55": {"informacion_personal": {"user_id": "USA4945894", "genero": "Masculino", "nombres": "Ezra Maxwell", "apellidos": "Cox Freeman", "lugar_nacimiento": "Brasil, Brasília", "estado_civil": "Viudo", "edad": 83, "religion": "Confucianismo", "postura_politica": "Liberalismo"}, "informacion_demografica": {"profesiones": ["Periodista"], "edad": 34, "lugar_nacimiento": "Argentina, Tucumán"}, "gustos": {"hobbies": ["Magia", "Tetherball", "Yoga"], "colores_favoritos": ["Dorado"], "equipo_futbol": ["América (México)"], "mascotas": ["Iguana", "Pájaro", "Hurón", "Cuy", "Hamster"], "modelos_autos": ["BMW Serie 3", "Opel Corsa"], "paise_conocidos": ["Italia", "Cuba", "Surinam", "Zambia", "Siria", "Rusia", "Chile", "Eslovaquia", "Mozambique", "Uruguay", "España", "Guyana", "Hungría", "Lesoto", "Guinea-Bisáu", "Islas Marshall", "Vietnam", "Bután"]}, "salud": {"enfermedades_raras": ["Hipertensión pulmonar primaria", "Síndrome de Tourette"], "alergias": ["Alergia al polvo", "Alergia al níquel", "Alergia al jabón", "Alergia a los medicamentos"], "deportes_practicados": []}, "habilidades": {"habilidades_tecnicas": ["Inteligencia artificial"], "habilidades_personales": ["Trabajo en equipo", "Flexibilidad"], "habilidades_varias": ["Deportes", "Primeros auxilios", "Idiomas"]}}}