{"3d7756e5-6620-4adf-8ff4-6405cbbe7daf": {"informacion_personal": {"user_id": "USA7125998", "genero": "Femenino", "nombres": "Anna Vivian", "apellidos": "Black Lane", "lugar_nacimiento": "Argentina, Buenos Aires", "estado_civil": "Viudo", "edad": 104, "religion": "Budismo", "postura_politica": "Socialismo"}, "informacion_demografica": {"profesiones": [], "edad": 94, "lugar_nacimiento": "Brasil, Curitiba"}, "gustos": {"hobbies": ["Torball", "Segway polo", "Magia", "Vigoro"], "colores_favoritos": ["Turquesa"], "equipo_futbol": ["Palmeiras (Brasil)"], "mascotas": ["Ninguno", "Perro", "Hurón", "Pájaro", "Axolote"], "modelos_autos": [], "paise_conocidos": ["Mozambique", "Alemania", "Birmania", "Uzbekistán", "San Vicente y las Granadinas", "Laos", "Argelia", "Costa de Marfil", "República Dominicana", "Finlandia", "Liechtenstein", "Maldivas", "Baréin", "Zimbabue"]}, "salud": {"enfermedades_raras": ["Síndrome de Guillain-Barré", "Síndrome de Angelman", "Distrofia muscular de Duchenne"], "alergias": ["Alergia a los sulfamidas", "Alergia a los mariscos"], "deportes_practicados": ["Gimnasia", "Boxeo", "Golf"]}, "habilidades": {"habilidades_tecnicas": ["Desarrollo móvil", "Machine learning", "Desarrollo de realidad virtual y aumentada", "Redes y seguridad informática", "Diseño gráfico"], "habilidades_personales": ["Proactividad", "Pensamiento crítico"], "habilidades_varias": ["Mecánica básica", "Cerámica", "Escritura creativa"]}}}