{"f8918f2a-bcca-41c3-a40c-3aacbf1665f5": {"informacion_personal": {"user_id": "USA8209971", "genero": "Femenino", "nombres": "Lucia Adriana", "apellidos": "Morales Bradley", "lugar_nacimiento": "Colombia, Cali", "estado_civil": "Casado", "edad": 95, "religion": "Islam", "postura_politica": "Socialismo"}, "informacion_demografica": {"profesiones": ["Bombero", "Panadero", "Psicólogo"], "edad": 99, "lugar_nacimiento": "Brasil, Curitiba"}, "gustos": {"hobbies": ["Aeróbic", "Tetherball", "Escalada en hielo", "Kayak polo", "Vóley"], "colores_favoritos": ["Azul", "Lavanda"], "equipo_futbol": ["Sao Paulo FC (Brasil)"], "mascotas": ["Hamster", "Chinchilla"], "modelos_autos": [], "paise_conocidos": ["Zimbabue", "Micronesia", "Botsuana", "Palaos", "Mozambique", "Maldivas", "Lituania", "Armenia", "Serbia", "Comoras", "Barbados", "Panamá", "Nauru", "Países Bajos", "Nicaragua", "Ruanda", "Venezuela", "Granada"]}, "salud": {"enfermedades_raras": ["Distrofia muscular de Duchenne", "Síndrome de Sturge-Weber", "Enfermedad de Wilson"], "alergias": ["Alergia a los medicamentos", "Alergia a los mariscos"], "deportes_practicados": ["Béisbol", "Tenis"]}, "habilidades": {"habilidades_tecnicas": [], "habilidades_personales": ["Honestidad", "Habilidades interpersonales", "Resolución de problemas", "Flexibilidad"], "habilidades_varias": ["Cerámica", "Dibujo y pintura", "Jardinería"]}}}