{"eb0a48bb-7ff3-4973-bc3f-de0d3409a6a1": {"informacion_personal": {"user_id": "USA8580182", "genero": "Femenino", "nombres": "Isabelle Nora", "apellidos": "Price Daniels", "lugar_nacimiento": "Ecuador, Ambato", "estado_civil": "Viudo", "edad": 39, "religion": "Ninguna", "postura_politica": "Ninguna"}, "informacion_demografica": {"profesiones": ["Panadero"], "edad": 20, "lugar_nacimiento": "Ecuador, Manta"}, "gustos": {"hobbies": ["Muay Thai", "Vóley", "Kickboxing", "Volleyball"], "colores_favoritos": ["Rosa", "Marrón", "Gris"], "equipo_futbol": ["Barcelona SC (Ecuador)"], "mascotas": ["Axolote", "Tarántula", "Perro"], "modelos_autos": ["Suzuki Swift", "Peugeot 208"], "paise_conocidos": ["Botsuana", "Egipto", "Guinea-Bisáu", "República del Congo", "Suazilandia", "Sudán", "Eritrea"]}, "salud": {"enfermedades_raras": ["Síndrome de Patau"], "alergias": [], "deportes_practicados": ["Surf", "Skateboarding"]}, "habilidades": {"habilidades_tecnicas": ["Inteligencia artificial", "Redes y seguridad informática", "Marketing digital", "Diseño gráfico", "Administración de sistemas"], "habilidades_personales": ["Adaptabilidad", "Habilidad de negociación", "Creatividad", "Responsabilidad", "Proactividad"], "habilidades_varias": ["Carpintería", "Jardinería", "Buceo"]}}}