{"18abe4a2-3fe7-4b54-9afc-5b9ab918e4ad": {"informacion_personal": {"user_id": "USA9596469", "genero": "Femenino", "nombres": "Jamie Maria", "apellidos": "Hall Peterson", "lugar_nacimiento": "Colombia, Ibagué", "estado_civil": "Separado", "edad": 51, "religion": "Sijismo", "postura_politica": "Populismo"}, "informacion_demografica": {"profesiones": ["Abogado"], "edad": 59, "lugar_nacimiento": "Ecuador, Esmeraldas"}, "gustos": {"hobbies": ["Women's lacrosse"], "colores_favoritos": ["Rojo"], "equipo_futbol": ["Sao Paulo FC (Brasil)"], "mascotas": ["Gato", "Tortuga"], "modelos_autos": ["Citroën C3", "Peugeot 208", "Chevrolet Onix"], "paise_conocidos": ["Chad", "Brunéi", "Turkmenistán", "Uganda", "Bahamas", "Arabia Saudita", "Yibuti", "Países Bajos", "Belice", "Francia", "Australia", "Emiratos Árabes Unidos", "Fiyi", "Jamaica"]}, "salud": {"enfermedades_raras": [], "alergias": ["Alergia a las picaduras de insectos", "Alergia a los medicamentos"], "deportes_practicados": ["Skateboarding", "Vóley"]}, "habilidades": {"habilidades_tecnicas": ["Diseño gráfico", "Desarrollo web", "Análisis de datos", "Desarrollo de realidad virtual y aumentada", "Manejo de bases de datos"], "habilidades_personales": [], "habilidades_varias": ["Artes marciales", "Yoga", "Jardinería", "Cerámica"]}}}